.stestr.conf
.travis.yml
AUTHORS
ChangeLog
LICENSE
README.rst
requirements.txt
setup.cfg
setup.py
test-requirements.txt
tox.ini
doc/source/conf.py
doc/source/index.rst
doc/source/pymochad.rst
doc/source/readme.rst
pymochad/__init__.py
pymochad/controller.py
pymochad/device.py
pymochad/exceptions.py
pymochad.egg-info/PKG-INFO
pymochad.egg-info/SOURCES.txt
pymochad.egg-info/dependency_links.txt
pymochad.egg-info/not-zip-safe
pymochad.egg-info/pbr.json
pymochad.egg-info/requires.txt
pymochad.egg-info/top_level.txt
pymochad/tests/__init__.py
pymochad/tests/base.py
pymochad/tests/test_controller.py