Metadata-Version: 1.1
Name: pymochad
Version: 0.2.0
Summary: A python library for interacting with moch
Home-page: UNKNOWN
Author: Matthew Treinish
Author-email: mtreinish@kortar.org
License: UNKNOWN
Platform: UNKNOWN
Classifier: License :: OSI Approved :: GNU General Public License v3 (GPLv3)
Classifier: Programming Language :: Python
Classifier: Programming Language :: Python :: 2
Classifier: Programming Language :: Python :: 2.7
Classifier: Programming Language :: Python :: 3
Classifier: Programming Language :: Python :: 3.4
Classifier: Programming Language :: Python :: 3.5
Classifier: Programming Language :: Python :: 3.6
